fastdjt/__init__.py
fastdjt/cookiecutter-django-main/.editorconfig
fastdjt/cookiecutter-django-main/.gitattributes
fastdjt/cookiecutter-django-main/.github/CONTRIBUTORS-template.md
fastdjt/cookiecutter-django-main/.github/FUNDING.yml
fastdjt/cookiecutter-django-main/.github/ISSUE_TEMPLATE/bug.md
fastdjt/cookiecutter-django-main/.github/ISSUE_TEMPLATE/feature.md
fastdjt/cookiecutter-django-main/.github/ISSUE_TEMPLATE/paid-support.md
fastdjt/cookiecutter-django-main/.github/ISSUE_TEMPLATE/question.md
fastdjt/cookiecutter-django-main/.github/PULL_REQUEST_TEMPLATE.md
fastdjt/cookiecutter-django-main/.github/changelog-template.md
fastdjt/cookiecutter-django-main/.github/contributors.json
fastdjt/cookiecutter-django-main/.github/dependabot.yml
fastdjt/cookiecutter-django-main/.github/workflows/align-versions.yml
fastdjt/cookiecutter-django-main/.github/workflows/ci.yml
fastdjt/cookiecutter-django-main/.github/workflows/dependabot-uv-lock.yml
fastdjt/cookiecutter-django-main/.github/workflows/django-issue-checker.yml
fastdjt/cookiecutter-django-main/.github/workflows/issue-manager.yml
fastdjt/cookiecutter-django-main/.github/workflows/pre-commit-autoupdate.yml
fastdjt/cookiecutter-django-main/.github/workflows/update-changelog.yml
fastdjt/cookiecutter-django-main/.github/workflows/update-contributors.yml
fastdjt/cookiecutter-django-main/.gitignore
fastdjt/cookiecutter-django-main/.pre-commit-config.yaml
fastdjt/cookiecutter-django-main/.pyup.yml
fastdjt/cookiecutter-django-main/.readthedocs.yaml
fastdjt/cookiecutter-django-main/CHANGELOG.md
fastdjt/cookiecutter-django-main/CODE_OF_CONDUCT.md
fastdjt/cookiecutter-django-main/CONTRIBUTING.md
fastdjt/cookiecutter-django-main/CONTRIBUTORS.md
fastdjt/cookiecutter-django-main/LICENSE
fastdjt/cookiecutter-django-main/README.md
fastdjt/cookiecutter-django-main/cookiecutter.json
fastdjt/cookiecutter-django-main/docs/1-getting-started/project-generation-options.rst
fastdjt-0.1.8.dist-info/WHEEL
fastdjt-0.1.8.dist-info/entry_points.txt
fastdjt-0.1.8.dist-info/METADATA
fastdjt-0.1.8.dist-info/RECORD
