Metadata-Version: 2.3
Name: fastdjt
Version: 0.1.8
Summary: 一个快速生成django项目框架的工具
Author: lipanpan
Author-email: lipanpan <lipanpanmail@163.com>
Requires-Dist: cookiecutter>=2.6.0
Requires-Dist: fire>=0.7.1
Requires-Dist: pyperclip>=1.11.0
Requires-Dist: toml>=0.10.2
Requires-Python: ~=3.13.0
